{
  "tasks": [
    {
      "id": 1,
      "name": "First Task Modified - Once more",
      "isTemplate": false,
      "state": "active",
      "description": "First active task desc, but modified.\nWith better description.",
      "priority": "Low"
    },
    {
      "id": 2,
      "name": "Second Task",
      "isTemplate": false,
      "state": "active",
      "description": "",
      "priority": "Low"
    },
    {
      "id": 3,
      "name": "Third Task",
      "isTemplate": false,
      "state": "active",
      "description": "Third active task desc",
      "priority": "Low"
    },
    {
      "id": 4,
      "name": "Nineth Task",
      "isTemplate": false,
      "state": "active",
      "description": "Second active task desc",
      "priority": "High"
    },
    {
      "id": 5,
      "name": "Tenth task",
      "isTemplate": false,
      "state": "active",
      "description": "",
      "priority": "High"
    },
    {
      "id": 6,
      "name": "Twenty-first task",
      "isTemplate": false,
      "state": "backlog",
      "description": "This tasks for backlog and has high priority",
      "priority": "High"
    },
    {
      "id": 7,
      "name": "Twenty-second Task",
      "isTemplate": false,
      "state": "backlog",
      "description": "This tasks for backlog and has high priority",
      "priority": "High"
    }
  ],
  "templates": [
    {
      "key": 0,
      "name": "Do push-ups"
    },
    {
      "key": 1,
      "name": "Run for a 100 meters"
    }
  ]
}